wafer_lsp/__init__.py
wafer_lsp/__main__.py
wafer_lsp/server.py
wafer_lsp/analyzers/__init__.py
wafer_lsp/analyzers/compiler_integration.py
wafer_lsp/analyzers/docs_index.py
wafer_lsp/handlers/__init__.py
wafer_lsp/handlers/code_action.py
wafer_lsp/handlers/code_lens.py
wafer_lsp/handlers/completion.py
wafer_lsp/handlers/diagnostics.py
wafer_lsp/handlers/document_symbol.py
wafer_lsp/handlers/hip_diagnostics.py
wafer_lsp/handlers/hover.py
wafer_lsp/handlers/inlay_hint.py
wafer_lsp/handlers/semantic_tokens.py
wafer_lsp/handlers/workspace_symbol.py
wafer_lsp/languages/README.md
wafer_lsp/languages/__init__.py
wafer_lsp/languages/converter.py
wafer_lsp/languages/detector.py
wafer_lsp/languages/parser_manager.py
wafer_lsp/languages/registry.py
wafer_lsp/languages/types.py
wafer_lsp/parsers/__init__.py
wafer_lsp/parsers/base_parser.py
wafer_lsp/parsers/cuda_parser.py
wafer_lsp/parsers/cutedsl_parser.py
wafer_lsp/parsers/hip_parser.py
wafer_lsp/services/__init__.py
wafer_lsp/services/analysis_service.py
wafer_lsp/services/docs_service.py
wafer_lsp/services/document_service.py
wafer_lsp/services/hip_docs.py
wafer_lsp/services/hip_hover_service.py
wafer_lsp/services/hover_service.py
wafer_lsp/services/language_registry_service.py
wafer_lsp/services/position_service.py
wafer_lsp/utils/__init__.py
wafer_lsp/utils/lsp_helpers.py
wafer_lsp-0.1.27.dist-info/METADATA
wafer_lsp-0.1.27.dist-info/WHEEL
wafer_lsp-0.1.27.dist-info/entry_points.txt
wafer_lsp-0.1.27.dist-info/RECORD
